firescipy/__init__.py
firescipy/constants.py
firescipy/utils.py
firescipy/handcalculation/__init__.py
firescipy/handcalculation/design_fires.py
firescipy/microscale/__init__.py
firescipy/microscale/microscale.py
firescipy/pyrolysis/__init__.py
firescipy/pyrolysis/kinetics.py
firescipy/pyrolysis/modeling.py
firescipy-0.0.6.dist-info/METADATA
firescipy-0.0.6.dist-info/WHEEL
firescipy-0.0.6.dist-info/licenses/LICENSE
firescipy-0.0.6.dist-info/licenses/NOTICE
firescipy-0.0.6.dist-info/RECORD
