Metadata-Version: 2.4
Name: firescipy
Version: 0.0.6
Summary: FireSciPy: Fundamental algorithms from the field of fire science, for computations with Python.
Project-URL: Repository, https://github.com/FireDynamics/FireSciPy
Project-URL: Documentation, https://firedynamics.github.io/FireSciPy/
Project-URL: Issues, https://github.com/FireDynamics/FireSciPy/issues
Author-email: Tristan Hehnen <you@example.com>, Lukas Arnold <you@example.com>
License: 
License-File: LICENSE
License-File: NOTICE
Keywords: FDS,Fire Safety Engineering,fire,kinetics,pyrolysis
Classifier: Intended Audience :: Science/Research
Classifier: License :: OSI Approved :: Mozilla Public License 2.0 (MPL 2.0)
Classifier: Operating System :: OS Independent
Classifier: Programming Language :: Python :: 3
Classifier: Topic :: Scientific/Engineering
Requires-Python: >=3.9
Requires-Dist: matplotlib>=3.4
Requires-Dist: numpy>=1.21
Requires-Dist: pandas>=1.3
Requires-Dist: scipy>=1.7
